{
  "version": "ESV",
  "book": "ISA",
  "chapter": 62,
  "verses": [
    {
      "verse": "1",
      "text": " For Zion’s sake I will not keep silent,"
    },
    {
      "verse": "#",
      "text": " until her righteousness goes forth as brightness,"
    },
    {
      "verse": "2",
      "text": " The nations shall see your righteousness,"
    },
    {
      "verse": "#",
      "text": " and you shall be called by a new name"
    },
    {
      "verse": "3",
      "text": "You shall be a crown of beauty in the hand of the Lord ,"
    },
    {
      "verse": "4",
      "text": " You shall no more be termed Forsaken,"
    },
    {
      "verse": "#",
      "text": "and your land shall no more be termed Desolate,"
    },
    {
      "verse": "#",
      "text": " but you shall be called My Delight Is in Her,"
    },
    {
      "verse": "#",
      "text": "and your land Married;"
    },
    {
      "verse": "5",
      "text": "For as a young man marries a young woman,"
    },
    {
      "verse": "#",
      "text": "so shall your sons marry you,"
    },
    {
      "verse": "#",
      "text": "so shall your God rejoice over you."
    },
    {
      "verse": "6",
      "text": "On your walls, O Jerusalem,"
    },
    {
      "verse": "#",
      "text": "I have set watchmen;"
    },
    {
      "verse": "7",
      "text": "and give him no rest"
    },
    {
      "verse": "#",
      "text": "and makes it a praise in the earth."
    },
    {
      "verse": "8",
      "text": "The Lord has sworn by his right hand"
    },
    {
      "verse": "#",
      "text": "“I will not again give your grain"
    },
    {
      "verse": "#",
      "text": " and foreigners shall not drink your wine"
    },
    {
      "verse": "9",
      "text": "but those who garner it shall eat it"
    },
    {
      "verse": "#",
      "text": "and those who gather it shall drink it"
    },
    {
      "verse": "#",
      "text": "in the courts of my sanctuary.”"
    },
    {
      "verse": "10",
      "text": "Go through, go through the gates;"
    },
    {
      "verse": "#",
      "text": " prepare the way for the people;"
    },
    {
      "verse": "#",
      "text": " build up, build up the highway;"
    },
    {
      "verse": "#",
      "text": " lift up a signal over the peoples."
    },
    {
      "verse": "11",
      "text": "Behold, the Lord has proclaimed"
    },
    {
      "verse": "#",
      "text": " Say to the daughter of Zion,"
    },
    {
      "verse": "#",
      "text": " “Behold, your salvation comes;"
    },
    {
      "verse": "12",
      "text": " And they shall be called The Holy People,"
    },
    {
      "verse": "#",
      "text": " and you shall be called Sought Out,"
    }
  ]
}