{
  "version": "ESV",
  "book": "JOB",
  "chapter": 30,
  "verses": [
    {
      "verse": "1",
      "text": "“But now they laugh at me,"
    },
    {
      "verse": "#",
      "text": "men who are younger than I,"
    },
    {
      "verse": "2",
      "text": "What could I gain from the strength of their hands,"
    },
    {
      "verse": "#",
      "text": " men whose vigor is gone?"
    },
    {
      "verse": "3",
      "text": "Through want and hard hunger"
    },
    {
      "verse": "#",
      "text": "they gnaw the dry ground by night in waste and desolation;"
    },
    {
      "verse": "4",
      "text": "they pick saltwort and the leaves of bushes,"
    },
    {
      "verse": "#",
      "text": "and the roots of the broom tree for their food."
    },
    {
      "verse": "5",
      "text": " They are driven out from human company;"
    },
    {
      "verse": "6",
      "text": "In the gullies of the torrents they must dwell,"
    },
    {
      "verse": "#",
      "text": "in holes of the earth and of the rocks."
    },
    {
      "verse": "7",
      "text": "Among the bushes they bray;"
    },
    {
      "verse": "#",
      "text": "under the nettles they huddle together."
    },
    {
      "verse": "8",
      "text": "A senseless, a nameless brood,"
    },
    {
      "verse": "9",
      "text": "“And now I have become their song;"
    },
    {
      "verse": "#",
      "text": "I am a byword to them."
    },
    {
      "verse": "10",
      "text": "They abhor me; they keep aloof from me;"
    },
    {
      "verse": "#",
      "text": "they do not hesitate to spit at the sight of me."
    },
    {
      "verse": "11",
      "text": "Because God has loosed my cord and humbled me,"
    },
    {
      "verse": "#",
      "text": "they have cast off restraint in my presence."
    },
    {
      "verse": "12",
      "text": "On my right hand the rabble rise;"
    },
    {
      "verse": "#",
      "text": "they cast up against me their ways of destruction."
    },
    {
      "verse": "13",
      "text": "They break up my path;"
    },
    {
      "verse": "#",
      "text": "they promote my calamity;"
    },
    {
      "verse": "14",
      "text": "As through a wide breach they come;"
    },
    {
      "verse": "15",
      "text": " Terrors are turned upon me;"
    },
    {
      "verse": "#",
      "text": "and my prosperity has passed away like a cloud."
    },
    {
      "verse": "16",
      "text": "“And now my soul is poured out within me;"
    },
    {
      "verse": "17",
      "text": " The night racks my bones,"
    },
    {
      "verse": "#",
      "text": "and the pain that gnaws me takes no rest."
    },
    {
      "verse": "18",
      "text": "With great force my garment is disfigured;"
    },
    {
      "verse": "19",
      "text": "God has cast me into the mire,"
    },
    {
      "verse": "#",
      "text": "and I have become like dust and ashes."
    },
    {
      "verse": "20",
      "text": "I cry to you for help and you do not answer me;"
    },
    {
      "verse": "21",
      "text": "You have turned cruel to me;"
    },
    {
      "verse": "#",
      "text": "with the might of your hand you persecute me."
    },
    {
      "verse": "22",
      "text": " You lift me up on the wind; you make me ride on it,"
    },
    {
      "verse": "23",
      "text": " For I know that you will bring me to death"
    },
    {
      "verse": "#",
      "text": "and to the house appointed for all living."
    },
    {
      "verse": "24",
      "text": "“Yet does not one in a heap of ruins stretch out his hand,"
    },
    {
      "verse": "#",
      "text": "and in his disaster cry for help?"
    },
    {
      "verse": "25",
      "text": "Did not I weep for him whose day was hard?"
    },
    {
      "verse": "26",
      "text": "But when I hoped for good, evil came,"
    },
    {
      "verse": "#",
      "text": "and when I waited for light, darkness came."
    },
    {
      "verse": "27",
      "text": "My inward parts are in turmoil and never still;"
    },
    {
      "verse": "#",
      "text": "days of affliction come to meet me."
    },
    {
      "verse": "28",
      "text": "I go about darkened, but not by the sun;"
    },
    {
      "verse": "#",
      "text": "I stand up in the assembly and cry for help."
    },
    {
      "verse": "29",
      "text": "I am a brother of jackals"
    },
    {
      "verse": "#",
      "text": "and a companion of ostriches."
    },
    {
      "verse": "30",
      "text": "My skin turns black and falls from me,"
    },
    {
      "verse": "#",
      "text": "and my bones burn with heat."
    },
    {
      "verse": "31",
      "text": "My lyre is turned to mourning,"
    },
    {
      "verse": "#",
      "text": "and my pipe to the voice of those who weep."
    }
  ]
}